{
  "updatedAt": "2026-05-17T08:34:05.852Z",
  "reddit": [
    {
      "id": "r1",
      "title": "RBA minutes hint at steady rates as inflation cools",
      "url": "https://example.com/r1",
      "source": "r/ausfinance",
      "publishedAt": "2026-05-10T22:10:00.000Z",
      "topics": [
        "macro",
        "rates"
      ]
    },
    {
      "id": "r2",
      "title": "Mid-term polling averages tighten in swing states",
      "url": "https://example.com/r2",
      "source": "r/neutralpolitics",
      "publishedAt": "2026-05-10T18:40:00.000Z",
      "topics": [
        "elections",
        "us"
      ]
    }
  ],
  "rss": [
    {
      "id": "rss:https://www.bbc.com/news/articles/c2l2p0wwzzdo?at_medium=RSS&amp;at_campaign=rss",
      "title": "WHO declares Ebola outbreak in DR Congo a global health emergency",
      "url": "https://www.bbc.com/news/articles/c2l2p0wwzzdo?at_medium=RSS&amp;at_campaign=rss",
      "source": "BBC World",
      "publishedAt": "2026-05-17T07:08:26.000Z",
      "topics": [
        "rss"
      ]
    },
    {
      "id": "rss:https://www.bbc.com/news/articles/c1j2zwe9g5no?at_medium=RSS&amp;at_campaign=rss",
      "title": "Hezbollah drone strike videos show evolving tactics against Israel",
      "url": "https://www.bbc.com/news/articles/c1j2zwe9g5no?at_medium=RSS&amp;at_campaign=rss",
      "source": "BBC World",
      "publishedAt": "2026-05-16T23:10:19.000Z",
      "topics": [
        "rss"
      ]
    },
    {
      "id": "rss:https://www.bbc.com/news/articles/cx2132w81jqo?at_medium=RSS&amp;at_campaign=rss",
      "title": "Taiwan insists it is independent after Trump warning",
      "url": "https://www.bbc.com/news/articles/cx2132w81jqo?at_medium=RSS&amp;at_campaign=rss",
      "source": "BBC World",
      "publishedAt": "2026-05-16T17:01:53.000Z",
      "topics": [
        "rss"
      ]
    },
    {
      "id": "rss:https://www.bbc.com/news/articles/c5ye480kxpmo?at_medium=RSS&amp;at_campaign=rss",
      "title": "Large-scale Ukrainian drone attack kills three in Moscow region, says Russia",
      "url": "https://www.bbc.com/news/articles/c5ye480kxpmo?at_medium=RSS&amp;at_campaign=rss",
      "source": "BBC World",
      "publishedAt": "2026-05-17T07:21:03.000Z",
      "topics": [
        "rss"
      ]
    },
    {
      "id": "rss:https://www.bbc.com/news/articles/cyv28pd4n22o?at_medium=RSS&amp;at_campaign=rss",
      "title": "Man drives car into pedestrians in Italy, injuring eight",
      "url": "https://www.bbc.com/news/articles/cyv28pd4n22o?at_medium=RSS&amp;at_campaign=rss",
      "source": "BBC World",
      "publishedAt": "2026-05-17T08:33:37.000Z",
      "topics": [
        "rss"
      ]
    },
    {
      "id": "rss:https://www.bbc.com/news/articles/c1w2gv1gdnjo?at_medium=RSS&amp;at_campaign=rss",
      "title": "Rescue diver dies during search for bodies of Italians who drowned in Maldives caves",
      "url": "https://www.bbc.com/news/articles/c1w2gv1gdnjo?at_medium=RSS&amp;at_campaign=rss",
      "source": "BBC World",
      "publishedAt": "2026-05-16T15:01:40.000Z",
      "topics": [
        "rss"
      ]
    },
    {
      "id": "rss:https://www.bbc.com/news/articles/c1l28lql137o?at_medium=RSS&amp;at_campaign=rss",
      "title": "Whale found dead near Danish island after German rescue operation",
      "url": "https://www.bbc.com/news/articles/c1l28lql137o?at_medium=RSS&amp;at_campaign=rss",
      "source": "BBC World",
      "publishedAt": "2026-05-16T17:01:28.000Z",
      "topics": [
        "rss"
      ]
    },
    {
      "id": "rss:https://www.bbc.com/news/articles/cx21d4pxq23o?at_medium=RSS&amp;at_campaign=rss",
      "title": "Trump-backed challenger defeats Republican senator who voted to convict president",
      "url": "https://www.bbc.com/news/articles/cx21d4pxq23o?at_medium=RSS&amp;at_campaign=rss",
      "source": "BBC World",
      "publishedAt": "2026-05-17T03:23:08.000Z",
      "topics": [
        "rss"
      ]
    }
  ],
  "trendingTopics": [
    {
      "topic": "rates",
      "score": 94
    },
    {
      "topic": "housing",
      "score": 81
    },
    {
      "topic": "elections",
      "score": 76
    },
    {
      "topic": "commodities",
      "score": 62
    }
  ],
  "summaries": [
    {
      "topicGroup": "Macro + FX",
      "bullets": [
        "AUD drifted higher against USD on softer US yields (mock).",
        "Energy complex mixed; Brent spot below near-dated futures (mock)."
      ],
      "asOf": "2026-05-11T07:30:00.000Z"
    },
    {
      "topicGroup": "Geopolitics",
      "bullets": [
        "Polling aggregates show narrow bands — treat as non-predictive stubs.",
        "Wire your preferred tracker for Ukraine control maps."
      ],
      "asOf": "2026-05-11T07:30:00.000Z"
    }
  ],
  "savedGroups": [
    {
      "id": "g1",
      "name": "Australia macro",
      "topics": [
        "rba",
        "cpi",
        "aud",
        "labour"
      ]
    },
    {
      "id": "g2",
      "name": "Elections desk",
      "topics": [
        "polls",
        "fivethirtyeight",
        "betting"
      ]
    }
  ]
}
